bedserver
