Metadata-Version: 1.1
Name: bedserver
Version: 0.1
Summary: A fast and simple bedfile server
Home-page: http://github.com/drio/bedserver
Author: David Rio
Author-email: driodeiros@gmail.com
License: https://github.com/drio/bedserver/blob/master/LICENSE
Platform: Posix; MacOS X; Windows
Classifier: Development Status :: 3 - Alpha
Classifier: Intended Audience :: Developers
Classifier: License :: OSI Approved :: MIT License
Classifier: Operating System :: OS Independent
Classifier: Topic :: Internet
